localthickness.py
localthickness-0.1.3.dist-info/LICENSE
localthickness-0.1.3.dist-info/METADATA
localthickness-0.1.3.dist-info/WHEEL
localthickness-0.1.3.dist-info/top_level.txt
localthickness-0.1.3.dist-info/RECORD
