Metadata-Version: 2.1
Name: localthickness
Version: 0.1.3
Summary: Fast local thickness in 3D and 2D.
Home-page: https://github.com/vedranaa/local-thickness
Author: VA Dahl and AB Dahl
Author-email: vand@dtu.dk, abda@dtu.dk
License: GPL-3.0 license
License-File: LICENSE
Requires-Dist: edt
Requires-Dist: numpy
